teilen/__init__.py
teilen/api.py
teilen/app.py
teilen/config.py
teilen/client/asset-manifest.json
teilen/client/favicon2.ico
teilen/client/favicon2.svg
teilen/client/file2.svg
teilen/client/folder2.svg
teilen/client/index.html
teilen/client/static/css/main.563ecd1a.css
teilen/client/static/js/main.846640e5.js
teilen/client/static/js/main.846640e5.js.LICENSE.txt
teilen-0.6.1.dist-info/METADATA
teilen-0.6.1.dist-info/WHEEL
teilen-0.6.1.dist-info/entry_points.txt
teilen-0.6.1.dist-info/top_level.txt
teilen-0.6.1.dist-info/RECORD
