Metadata-Version: 2.4
Name: teilen
Version: 0.6.1
Summary: a simple application to share data via http with python flask backend and react frontend
Home-page: https://pypi.org/project/teilen/
Author: Steffen Richters-Finger
Author-email: srichters@uni-muenster.de
License: MIT
Project-URL: Source, https://github.com/RichtersFinger/python-teilen
Classifier: Development Status :: 5 - Production/Stable
Classifier: Intended Audience :: End Users/Desktop
Classifier: Topic :: Communications
Classifier: Topic :: Communications :: File Sharing
Classifier: License :: OSI Approved :: MIT License
Classifier: Programming Language :: Python :: 3
Classifier: Programming Language :: Python :: 3.10
Classifier: Programming Language :: Python :: 3.11
Classifier: Programming Language :: Python :: 3.12
Classifier: Framework :: Flask
Requires-Python: >=3.10
Requires-Dist: Flask<4,>=3
Requires-Dist: gunicorn
Dynamic: author
Dynamic: author-email
Dynamic: classifier
Dynamic: description
Dynamic: description-content-type
Dynamic: home-page
Dynamic: license
Dynamic: project-url
Dynamic: requires-dist
Dynamic: requires-python
Dynamic: summary
